{
    "Result": [
        {
            "_id": "6614e1a80fc9660a5488b574",
            "pId": "0",
            "categoryName": "Dry Fruits",
            "categoryDescription": "e-mall-shop",
            "categoryImages": [],
            "isDeleted": false,
            "isActive": true,
            "createdAt": "2024-04-09T06:35:20.572Z",
            "updatedAt": "2024-04-09T06:35:20.572Z",
            "subcategories": [
                {
                    "_id": "6614e1de0fc9660a5488b575",
                    "pId": "6614e1a80fc9660a5488b574",
                    "categoryName": "Cashew",
                    "categoryDescription": "connecting people",
                    "categoryImages": [
                        "http://localhost:3001/product-category-images/1712644574154.png"
                    ],
                    "isDeleted": false,
                    "isActive": true,
                    "createdAt": "2024-04-09T06:36:14.246Z",
                    "updatedAt": "2024-04-09T06:36:14.246Z"
                },
                {
                    "_id": "6614f1bd1bf91338e88b330c",
                    "pId": "6614e1a80fc9660a5488b574",
                    "categoryName": "Almond",
                    "categoryDescription": "China",
                    "categoryImages": [],
                    "isDeleted": false,
                    "isActive": true,
                    "createdAt": "2024-04-09T07:43:57.559Z",
                    "updatedAt": "2024-04-09T07:43:57.559Z"
                },
                {
                    "_id": "66153263a98203197c2afe64",
                    "pId": "6614e1a80fc9660a5488b574",
                    "categoryName": "Walnut",
                    "categoryDescription": "All mobile phones are designed and manufactured by Motorola Mobility LLC, a wholly owned subsidiary of Lenovo.",
                    "categoryImages": [],
                    "isDeleted": false,
                    "isActive": true,
                    "createdAt": "2024-04-09T12:19:47.860Z",
                    "updatedAt": "2024-04-09T12:19:47.860Z"
                },
                {
                    "_id": "662790dc7acc8e00121fe28d",
                    "pId": "6614e1a80fc9660a5488b574",
                    "categoryName": "Dates",
                    "categoryDescription": "From Dried coconut",
                    "categoryImages": [],
                    "isDeleted": false,
                    "isActive": true,
                    "createdAt": "2024-04-23T10:43:40.571Z",
                    "updatedAt": "2024-04-23T10:45:37.132Z"
                }
            ]
        },
        {
            "_id": "662a624d7af30e0013145c20",
            "pId": "0",
            "categoryName": "Fresh Fruit",
            "categoryDescription": "Fresh fruit is good for heath",
            "categoryImages": [
                "http://localhost:3001/product-category-images/1714053709193.png"
            ],
            "isDeleted": false,
            "isActive": true,
            "createdAt": "2024-04-25T14:01:49.198Z",
            "updatedAt": "2024-04-25T14:01:49.198Z",
            "subcategories": []
        }
    ],
    "TotalCount": 2
}